{"Pelham Gardens": ["Allerton-Pelham Gardens"],
"St. George": ["West New Brighton-New Brighton-St. George"],
"New Springville": ["New Springville-Bloomfield-Travis"],
"Kingsbridge": ["Spuyten Duyvil-Kingsbridge"],
"Grasmere - Concord": ["Grasmere-Arrochar-Ft. Wadsworth"],
"Queens Village": ["Queens Village"],
"New Dorp": ["New Dorp-Midland Beach"],
"New Dorp Beach": ["New Dorp-Midland Beach"],
"Great Kills": ["Great Kills"],
"South Beach": ["Old Town-Dongan Hills-South Beach"],
"Castle Hill": ["Soundview-Castle Hill-Clason Point-Harding Park"],
"Westerleigh": ["Westerleigh"],
"Chelsea-Travis": ["New Springville-Bloomfield-Travis"],
"South Ozone Park": ["South Ozone Park"],
"Heartland Village": ["Todt Hill-Emerson Hill-Heartland Village-Lighthouse Hill"],
"Oakwood": ["Oakwood-Oakwood Beach"],
"Eltingville": ["Annadale-Huguenot-Prince's Bay-Eltingville"],
"Bellerose": ["Bellerose"],
"Woodhaven": ["Woodhaven"],
"Ozone Park": ["Ozone Park"],
"Clason Point": ["Soundview-Castle Hill-Clason Point-Harding Park"],
"Arverne": ["Hammels-Arverne-Edgemere"],
"Bedford Stuyvesant": ["Stuyvesant Heights"],
"Ocean Hill": ["Ocean Hill"],
"Crown Heights": ["Crown Heights North", "Crown Heights South"],
"Country Club": ["Pelham Bay-Country Club-City Island"],
"Grymes Hill": ["Grymes Hill-Clifton-Fox Hills"],
"Huguenot": ["Annadale-Huguenot-Prince's Bay-Eltingville"],
"Eltingville": ["Annadale-Huguenot-Prince's Bay-Eltingville"],
"St. Albans": ["St. Albans"],
"Broad Channel": ["Breezy Point-Belle Harbor-Rockaway Park-Broad Channel"],
"Tottenville": ["Charleston-Richmond Valley-Tottenville"],
"Emerson Hill": ["Todt Hill-Emerson Hill-Heartland Village-Lighthouse Hill"],
"New Brighton": ["West New Brighton-New Brighton-St. George", "New Brighton-Silver Lake"],
"Midland Beach": ["New Dorp-Midland Beach"],
"Prince's Bay": ["Annadale-Huguenot-Prince's Bay-Eltingville"],
"Old Town": ["Old Town-Dongan Hills-South Beach"],
"East New York": ["East New York"],
"Arrochar": ["Grasmere-Arrochar-Ft. Wadsworth"],
"Wakefield": ["Woodlawn-Wakefield"],
"Soundview": ["Soundview-Bruckner", "Soundview-Castle Hill-Clason Point-Harding Park"],
"Richmond Hill": ["Richmond Hill"],
"Brookville": ["Springfield Gardens South-Brookville"],
"Bushwick": ["Bushwick North", "Bushwick South"],
"Borough Park": ["Borough Park"],
"Rosedale": ["Rosedale"],
"Cambria Heights": ["Cambria Heights"],
"Dongan Hills": ["Old Town-Dongan Hills-South Beach"],
"Flatlands": ["Flatlands"],
"Eastchester": ["Eastchester-Edenwald-Baychester"],
"Hollis": ["Hollis"],
"Far Rockaway": ["Far Rockaway-Bayswater"],
"Laurelton": ["Laurelton"],
"Jamaica": ["Jamaica"],
"Rockaway Beach": ["Breezy Point-Belle Harbor-Rockaway Park-Broad Channel"],
"Jamaica Hills": ["Briarwood-Jamaica Hills"],
"Springfield Gardens": ["Springfield Gardens North", "Springfield Gardens South-Brookville"],
"Flatbush": ["Flatbush"],
"Woodrow": ["Rossville-Woodrow"],
"Bay Terrace": ["Ft. Totten-Bay Terrace-Clearview"],
"Canarsie": ["Canarsie"],
"Mariner's Harbor": ["Mariner's Harbor-Arlington-Port Ivory-Graniteville"],
"Port Ivory": ["Mariner's Harbor-Arlington-Port Ivory-Graniteville"],
"Annadale": ["Annadale-Huguenot-Prince's Bay-Eltingville"],
"Todt Hill": ["Todt Hill-Emerson Hill-Heartland Village-Lighthouse Hill"],
"West Brighton": ["West Brighton"],
"Rossville": ["Rossville-Woodrow"],
"Lighthouse Hill": ["Todt Hill-Emerson Hill-Heartland Village-Lighthouse Hill"]
}